{
    "namespace": "neko_c",

    ///////////////////////////////////////
    //
    // MAIN UI
    //
    ///////////////////////////////////////

    "weebs@loli.label": {
      "layer": 5,
      "text": "Minecraft : Wibu Edition",
      "font_type": "MinecraftTen"
    },

    ///////////////////////////////////////
    //
    // S E T T I N G S
    //
    ///////////////////////////////////////

    "logo_ui": { "type": "image", "texture": "textures/ui-x/icon/title", "size": [ "100%" , 95 ]},
    // Versi
    "version_title@custom_settings_section.fxn_label": { "text": "Version :" ,"shadow": false },
    "version_number@custom_settings_section.fxn_label": { "font_size":"large", "text": "v1.2.5 | Loli" , "shadow": true },
    "version_about@custom_settings_section.fxn_label": { "text": "Loli = Beta\nMilff = Stable" ,"shadow": false },

    // Build
    "build_title@custom_settings_section.fxn_label": { "text": "Build : " ,"shadow": false },
    "build_number@custom_settings_section.fxn_label": { "font_size":"large", "text": "087" , "shadow": true },
    "about@custom_settings_section.fxn_label": { "text": "Custom UI\nCreated By Farhan(Han)" ,"shadow": false }
}